arglink/__init__.py
arglink/core.py
arglink-1.0.4.dist-info/licenses/LICENSE
arglink-1.0.4.dist-info/METADATA
arglink-1.0.4.dist-info/WHEEL
arglink-1.0.4.dist-info/top_level.txt
arglink-1.0.4.dist-info/RECORD
