Metadata-Version: 2.4
Name: arglink
Version: 1.0.4
Summary: Linking an argument parser and a callable.
Author: Jiyuan Yang
License-Expression: MIT
Project-URL: Homepage, https://github.com/ygjiyn/arglink_project
Classifier: Programming Language :: Python :: 3
Classifier: Operating System :: OS Independent
Requires-Python: >=3.10
License-File: LICENSE
Dynamic: license-file
